<scores><score><game_id>1</game_id><user_id>2</user_id><user_score>1.0</user_score><timestamp>2020-06-24 10:07:25</timestamp></score><score><game_id>1</game_id><user_id>4</user_id><user_score>6.0</user_score><timestamp>2020-07-29 17:36:45</timestamp></score><score><game_id>1</game_id><user_id>1</user_id><user_score>7</user_score><timestamp>2020-07-29 17:45:39</timestamp></score><score><game_id>1</game_id><user_id>3</user_id><user_score>3</user_score><timestamp>2020-07-29 17:50:45</timestamp></score><score><game_id>1</game_id><user_id>01</user_id><user_score>6</user_score><timestamp>2020-07-29 18:08:05</timestamp></score></scores>